{
  "assets": [
    {
      "filename": "autism-800x600.png",
      "path": "/assets/autism-800x600.png",
      "url": "/assets/autism-800x600.png",
      "dimensions": { "width": 800, "height": 600 },
      "ratio": "4:3",
      "ratioCategory": "4:3",
      "type": "PNG",
      "size": "Unknown",
      "recommendedFor": "Featured Articles (Positions 1-4)"
    },
    {
      "filename": "autism-1200X675.png",
      "path": "/assets/autism-1200X675.png",
      "url": "/assets/autism-1200X675.png",
      "dimensions": { "width": 1200, "height": 675 },
      "ratio": "16:9",
      "ratioCategory": "16:9",
      "type": "PNG",
      "size": "Unknown",
      "recommendedFor": "Regular Articles (Positions 5+)"
    },
    {
      "filename": "fractured-800x600.png",
      "path": "/assets/fractured-800x600.png",
      "url": "/assets/fractured-800x600.png",
      "dimensions": { "width": 800, "height": 600 },
      "ratio": "4:3",
      "ratioCategory": "4:3",
      "type": "PNG",
      "size": "Unknown",
      "recommendedFor": "Featured Articles (Positions 1-4)"
    },
    {
      "filename": "ICE-400x225.png",
      "path": "/assets/ICE-400x225.png",
      "url": "/assets/ICE-400x225.png",
      "dimensions": { "width": 400, "height": 225 },
      "ratio": "16:9",
      "ratioCategory": "16:9",
      "type": "PNG",
      "size": "Unknown",
      "recommendedFor": "Regular Articles (Positions 5+)"
    },
    {
      "filename": "injustice-correct-800x500.png",
      "path": "/assets/injustice-correct-800x500.png",
      "url": "/assets/injustice-correct-800x500.png",
      "dimensions": { "width": 800, "height": 500 },
      "ratio": "8:5",
      "ratioCategory": "other",
      "type": "PNG",
      "size": "Unknown",
      "recommendedFor": "Custom Use"
    },
    {
      "filename": "Lady-liberty-1600x1000.png",
      "path": "/assets/Lady-liberty-1600x1000.png",
      "url": "/assets/Lady-liberty-1600x1000.png",
      "dimensions": { "width": 1600, "height": 1000 },
      "ratio": "8:5",
      "ratioCategory": "other",
      "type": "PNG",
      "size": "Unknown",
      "recommendedFor": "Custom Use"
    },
    {
      "filename": "autism-1000x1250.png",
      "path": "/assets/autism-1000x1250.png",
      "url": "/assets/autism-1000x1250.png",
      "dimensions": { "width": 1000, "height": 1250 },
      "ratio": "4:5",
      "ratioCategory": "other",
      "type": "PNG",
      "size": "Unknown",
      "recommendedFor": "Custom Use"
    },
    {
      "filename": "Antfia.png",
      "path": "/assets/Antfia.png",
      "url": "/assets/Antfia.png",
      "dimensions": { "width": 0, "height": 0 },
      "ratio": "Unknown",
      "ratioCategory": "other",
      "type": "PNG",
      "size": "Unknown",
      "recommendedFor": "Custom Use"
    },
    {
      "filename": "antifa.png",
      "path": "/assets/antifa.png",
      "url": "/assets/antifa.png",
      "dimensions": { "width": 0, "height": 0 },
      "ratio": "Unknown",
      "ratioCategory": "other",
      "type": "PNG",
      "size": "Unknown",
      "recommendedFor": "Custom Use"
    },
    {
      "filename": "asd-medical.png",
      "path": "/assets/asd-medical.png",
      "url": "/assets/asd-medical.png",
      "dimensions": { "width": 0, "height": 0 },
      "ratio": "Unknown",
      "ratioCategory": "other",
      "type": "PNG",
      "size": "Unknown",
      "recommendedFor": "Custom Use"
    },
    {
      "filename": "carbon.png",
      "path": "/assets/carbon.png",
      "url": "/assets/carbon.png",
      "dimensions": { "width": 0, "height": 0 },
      "ratio": "Unknown",
      "ratioCategory": "other",
      "type": "PNG",
      "size": "Unknown",
      "recommendedFor": "Custom Use"
    },
    {
      "filename": "CO2.png",
      "path": "/assets/CO2.png",
      "url": "/assets/CO2.png",
      "dimensions": { "width": 0, "height": 0 },
      "ratio": "Unknown",
      "ratioCategory": "other",
      "type": "PNG",
      "size": "Unknown",
      "recommendedFor": "Custom Use"
    },
    {
      "filename": "Corporations Media.png",
      "path": "/assets/Corporations Media.png",
      "url": "/assets/Corporations Media.png",
      "dimensions": { "width": 0, "height": 0 },
      "ratio": "Unknown",
      "ratioCategory": "other",
      "type": "PNG",
      "size": "Unknown",
      "recommendedFor": "Custom Use"
    },
    {
      "filename": "courts-injustice.png",
      "path": "/assets/courts-injustice.png",
      "url": "/assets/courts-injustice.png",
      "dimensions": { "width": 0, "height": 0 },
      "ratio": "Unknown",
      "ratioCategory": "other",
      "type": "PNG",
      "size": "Unknown",
      "recommendedFor": "Custom Use"
    },
    {
      "filename": "Farmers.png",
      "path": "/assets/Farmers.png",
      "url": "/assets/Farmers.png",
      "dimensions": { "width": 0, "height": 0 },
      "ratio": "Unknown",
      "ratioCategory": "other",
      "type": "PNG",
      "size": "Unknown",
      "recommendedFor": "Custom Use"
    },
    {
      "filename": "fractured-400 x 250.png",
      "path": "/assets/fractured-400 x 250.png",
      "url": "/assets/fractured-400 x 250.png",
      "dimensions": { "width": 400, "height": 250 },
      "ratio": "8:5",
      "ratioCategory": "other",
      "type": "PNG",
      "size": "Unknown",
      "recommendedFor": "Custom Use"
    },
    {
      "filename": "injustice-800x500.png",
      "path": "/assets/injustice-800x500.png",
      "url": "/assets/injustice-800x500.png",
      "dimensions": { "width": 800, "height": 500 },
      "ratio": "8:5",
      "ratioCategory": "other",
      "type": "PNG",
      "size": "Unknown",
      "recommendedFor": "Custom Use"
    },
    {
      "filename": "logo.png",
      "path": "/assets/logo.png",
      "url": "/assets/logo.png",
      "dimensions": { "width": 0, "height": 0 },
      "ratio": "Unknown",
      "ratioCategory": "other",
      "type": "PNG",
      "size": "Unknown",
      "recommendedFor": "Custom Use"
    },
    {
      "filename": "Lynching.jpg",
      "path": "/assets/Lynching.jpg",
      "url": "/assets/Lynching.jpg",
      "dimensions": { "width": 0, "height": 0 },
      "ratio": "Unknown",
      "ratioCategory": "other",
      "type": "JPEG",
      "size": "Unknown",
      "recommendedFor": "Custom Use"
    },
    {
      "filename": "Nation of Contrast.png",
      "path": "/assets/Nation of Contrast.png",
      "url": "/assets/Nation of Contrast.png",
      "dimensions": { "width": 0, "height": 0 },
      "ratio": "Unknown",
      "ratioCategory": "other",
      "type": "PNG",
      "size": "Unknown",
      "recommendedFor": "Custom Use"
    },
    {
      "filename": "news-owl.png",
      "path": "/assets/news-owl.png",
      "url": "/assets/news-owl.png",
      "dimensions": { "width": 0, "height": 0 },
      "ratio": "Unknown",
      "ratioCategory": "other",
      "type": "PNG",
      "size": "Unknown",
      "recommendedFor": "Custom Use"
    },
    {
      "filename": "owl-stack-books.png",
      "path": "/assets/owl-stack-books.png",
      "url": "/assets/owl-stack-books.png",
      "dimensions": { "width": 0, "height": 0 },
      "ratio": "Unknown",
      "ratioCategory": "other",
      "type": "PNG",
      "size": "Unknown",
      "recommendedFor": "Custom Use"
    },
    {
      "filename": "owl-standing.png",
      "path": "/assets/owl-standing.png",
      "url": "/assets/owl-standing.png",
      "dimensions": { "width": 0, "height": 0 },
      "ratio": "Unknown",
      "ratioCategory": "other",
      "type": "PNG",
      "size": "Unknown",
      "recommendedFor": "Custom Use"
    },
    {
      "filename": "owl-teacup.png",
      "path": "/assets/owl-teacup.png",
      "url": "/assets/owl-teacup.png",
      "dimensions": { "width": 0, "height": 0 },
      "ratio": "Unknown",
      "ratioCategory": "other",
      "type": "PNG",
      "size": "Unknown",
      "recommendedFor": "Custom Use"
    },
    {
      "filename": "pain-killers.png",
      "path": "/assets/pain-killers.png",
      "url": "/assets/pain-killers.png",
      "dimensions": { "width": 0, "height": 0 },
      "ratio": "Unknown",
      "ratioCategory": "other",
      "type": "PNG",
      "size": "Unknown",
      "recommendedFor": "Custom Use"
    },
    {
      "filename": "recession_uncle-sam.png",
      "path": "/assets/recession_uncle-sam.png",
      "url": "/assets/recession_uncle-sam.png",
      "dimensions": { "width": 0, "height": 0 },
      "ratio": "Unknown",
      "ratioCategory": "other",
      "type": "PNG",
      "size": "Unknown",
      "recommendedFor": "Custom Use"
    },
    {
      "filename": "screen-shot.png",
      "path": "/assets/screen-shot.png",
      "url": "/assets/screen-shot.png",
      "dimensions": { "width": 0, "height": 0 },
      "ratio": "Unknown",
      "ratioCategory": "other",
      "type": "PNG",
      "size": "Unknown",
      "recommendedFor": "Custom Use"
    },
    {
      "filename": "The News Curator.png",
      "path": "/assets/The News Curator.png",
      "url": "/assets/The News Curator.png",
      "dimensions": { "width": 0, "height": 0 },
      "ratio": "Unknown",
      "ratioCategory": "other",
      "type": "PNG",
      "size": "Unknown",
      "recommendedFor": "Custom Use"
    },
    {
      "filename": "The News Curator.webp",
      "path": "/assets/The News Curator.webp",
      "url": "/assets/The News Curator.webp",
      "dimensions": { "width": 0, "height": 0 },
      "ratio": "Unknown",
      "ratioCategory": "other",
      "type": "WebP",
      "size": "Unknown",
      "recommendedFor": "Custom Use"
    },
    {
      "filename": "Trump_August.png",
      "path": "/assets/Trump_August.png",
      "url": "/assets/Trump_August.png",
      "dimensions": { "width": 0, "height": 0 },
      "ratio": "Unknown",
      "ratioCategory": "other",
      "type": "PNG",
      "size": "Unknown",
      "recommendedFor": "Custom Use"
    },
    {
      "filename": "Truth Crisis.png",
      "path": "/assets/Truth Crisis.png",
      "url": "/assets/Truth Crisis.png",
      "dimensions": { "width": 0, "height": 0 },
      "ratio": "Unknown",
      "ratioCategory": "other",
      "type": "PNG",
      "size": "Unknown",
      "recommendedFor": "Custom Use"
    },
    {
      "filename": "Tylenol.png",
      "path": "/assets/Tylenol.png",
      "url": "/assets/Tylenol.png",
      "dimensions": { "width": 0, "height": 0 },
      "ratio": "Unknown",
      "ratioCategory": "other",
      "type": "PNG",
      "size": "Unknown",
      "recommendedFor": "Custom Use"
    },
    {
      "filename": "US Crisis.png",
      "path": "/assets/US Crisis.png",
      "url": "/assets/US Crisis.png",
      "dimensions": { "width": 0, "height": 0 },
      "ratio": "Unknown",
      "ratioCategory": "other",
      "type": "PNG",
      "size": "Unknown",
      "recommendedFor": "Custom Use"
    },
    {
      "filename": "compact-logo.svg",
      "path": "/assets/compact-logo.svg",
      "url": "/assets/compact-logo.svg",
      "dimensions": { "width": 0, "height": 0 },
      "ratio": "Vector",
      "ratioCategory": "other",
      "type": "SVG",
      "size": "Unknown",
      "recommendedFor": "Logos and Icons"
    },
    {
      "filename": "logo-v3.svg",
      "path": "/assets/logo-v3.svg",
      "url": "/assets/logo-v3.svg",
      "dimensions": { "width": 0, "height": 0 },
      "ratio": "Vector",
      "ratioCategory": "other",
      "type": "SVG",
      "size": "Unknown",
      "recommendedFor": "Logos and Icons"
    },
    {
      "filename": "navbar-logo.svg",
      "path": "/assets/navbar-logo.svg",
      "url": "/assets/navbar-logo.svg",
      "dimensions": { "width": 0, "height": 0 },
      "ratio": "Vector",
      "ratioCategory": "other",
      "type": "SVG",
      "size": "Unknown",
      "recommendedFor": "Logos and Icons"
    }
  ]
}
